{
  "camera_index": 0,
  "cooldown_sec": 0.7,

  "actions": {
    "OPEN_PALM": {
      "type": "key_press",
      "key": "enter"
    },

    "FIST": {
      "type": "key_press",
      "key": "esc"
    },

    "POINT": {
      "type": "key_press",
      "key": "tab"
    },

    "THUMBS_UP": {
      "type": "hotkey",
      "keys": ["ctrl", "w"]
    },

    "PINCH": {
      "type": "mouse_click",
      "description": "Başparmak + İşaret Parmağı = Click"
    },

    "ONE_FINGER": {
      "type": "message",
      "text": "Merhaba! 👋"
    },

    "TWO_FINGERS": {
      "type": "message",
      "text": "Nasılsın? 😊"
    },

    "THREE_FINGERS": {
      "type": "message",
      "text": "İyiyim, teşekkürler! 👍"
    },

    "FOUR_FINGERS": {
      "type": "message",
      "text": "Evet! ✅"
    },

    "FIVE_FINGERS": {
      "type": "message",
      "text": "Hayır! ❌"
    },

    "MOUSE_MOVE": {
      "type": "mouse_move",
      "description": "İşaret parmağı ile cursor kontrol (otomatik)"
    }
  }
}
